setup.cfg
setup.py
tensorforce_client/__init__.py
tensorforce_client/__main__.py
tensorforce_client/cluster.py
tensorforce_client/commands.py
tensorforce_client/experiment.py
tensorforce_client/tfcli.py
tensorforce_client/utils.py
tensorforce_client.egg-info/PKG-INFO
tensorforce_client.egg-info/SOURCES.txt
tensorforce_client.egg-info/dependency_links.txt
tensorforce_client.egg-info/entry_points.txt
tensorforce_client.egg-info/requires.txt
tensorforce_client.egg-info/top_level.txt
tensorforce_client/configs/experiment.yaml.jinja