Metadata-Version: 1.1
Name: tensorforce-client
Version: 0.1.0a5
Summary: A client to run experiments in the cloud using the TensorForce reinforcement learning library.
Home-page: https://github.com/reinforceio/tensorforce-client
Author: Reinforce.io & ducandu research
Author-email: sven.mika@ducandu.com
License: Apache 2.0
Download-URL: https://github.com/reinforceio/tensorforce-client/archive/0.1.0a5.tar.gz
Keywords: Reinforcement Learning,Cloud based RL,TensorForce,TensorFlow,Unreal Engine 4,Cloud Machine Learning with GPUs
Platform: UNKNOWN
